{
  "SavedPrefabs": [
    {
      "prefabName": "pounder",
      "dimension": 2,
      "worldPosition": {
        "x": -6.455711,
        "y": 0.4209881,
        "z": 9.447125
      },
      "quaternionRotation": {
        "x": 0.0,
        "y": 0.0,
        "z": 0.0,
        "w": 1.0
      },
      "floatData": null,
      "stringData": null
    },
    {
      "prefabName": "brush",
      "dimension": 2,
      "worldPosition": {
        "x": -3.58656931,
        "y": 1.00103354,
        "z": 15.0310526
      },
      "quaternionRotation": {
        "x": -0.65771234,
        "y": 0.00131929247,
        "z": -0.7532675,
        "w": 0.0008889121
      },
      "floatData": null,
      "stringData": null
    },
    {
      "prefabName": "green",
      "dimension": 2,
      "worldPosition": {
        "x": 1.00517011,
        "y": 0.4050245,
        "z": 12.8283234
      },
      "quaternionRotation": {
        "x": 0.0284691975,
        "y": 0.8901964,
        "z": -0.08078414,
        "w": -0.4474526
      },
      "floatData": {
        "fear": 0.0,
        "happiness": 1.0,
        "hunger": 0.005,
        "health": 1.0,
        "disruptance": 0.0,
        "curiosity": 0.0
      },
      "stringData": null
    },
    {
      "prefabName": "red",
      "dimension": 2,
      "worldPosition": {
        "x": 1.977615,
        "y": 0.276592374,
        "z": 3.37713027
      },
      "quaternionRotation": {
        "x": -1.94199652E-06,
        "y": -0.00204924215,
        "z": -4.55288937E-05,
        "w": 0.9999979
      },
      "floatData": {
        "fear": 0.0,
        "happiness": 1.0,
        "hunger": 0.005,
        "health": 1.0,
        "disruptance": 0.01,
        "curiosity": 0.0
      },
      "stringData": null
    },
    {
      "prefabName": "blue",
      "dimension": 2,
      "worldPosition": {
        "x": 1.99054742,
        "y": 0.399240077,
        "z": 8.421888
      },
      "quaternionRotation": {
        "x": 0.0,
        "y": -1.14686527E-08,
        "z": 0.0,
        "w": 1.0
      },
      "floatData": {
        "fear": 0.0,
        "happiness": 1.0,
        "hunger": 0.005,
        "health": 1.0,
        "disruptance": 0.0,
        "curiosity": 0.0
      },
      "stringData": null
    },
    {
      "prefabName": "seed",
      "dimension": 1,
      "worldPosition": {
        "x": -231.890961,
        "y": 4.280578,
        "z": -348.34082
      },
      "quaternionRotation": {
        "x": 0.0119115934,
        "y": -5.48155E-06,
        "z": 0.00795710552,
        "w": 0.9998974
      },
      "floatData": null,
      "stringData": null
    },
    {
      "prefabName": "seed",
      "dimension": 1,
      "worldPosition": {
        "x": -228.4873,
        "y": 4.34264,
        "z": -349.775452
      },
      "quaternionRotation": {
        "x": 0.00457420526,
        "y": 8.599831E-06,
        "z": 0.0005014066,
        "w": 0.99998945
      },
      "floatData": null,
      "stringData": null
    },
    {
      "prefabName": "seed",
      "dimension": 1,
      "worldPosition": {
        "x": 257.5124,
        "y": 3.78029847,
        "z": 232.892685
      },
      "quaternionRotation": {
        "x": 0.00497696176,
        "y": 9.09828E-05,
        "z": 0.041921027,
        "w": 0.9991086
      },
      "floatData": null,
      "stringData": null
    },
    {
      "prefabName": "seed",
      "dimension": 1,
      "worldPosition": {
        "x": -273.3956,
        "y": 11.1141033,
        "z": 378.353973
      },
      "quaternionRotation": {
        "x": 0.0105497865,
        "y": -5.67398965E-05,
        "z": 0.009364909,
        "w": 0.9999006
      },
      "floatData": null,
      "stringData": null
    },
    {
      "prefabName": "seed",
      "dimension": 1,
      "worldPosition": {
        "x": 264.251678,
        "y": 4.1158514,
        "z": 224.835876
      },
      "quaternionRotation": {
        "x": -0.0146505218,
        "y": -0.000504578638,
        "z": 0.0212594718,
        "w": 0.9996666
      },
      "floatData": null,
      "stringData": null
    },
    {
      "prefabName": "seed",
      "dimension": 1,
      "worldPosition": {
        "x": -273.344818,
        "y": 4.35031366,
        "z": -339.645966
      },
      "quaternionRotation": {
        "x": 0.00448078942,
        "y": 3.75323543E-05,
        "z": -0.000828380056,
        "w": 0.9999897
      },
      "floatData": null,
      "stringData": null
    },
    {
      "prefabName": "seed",
      "dimension": 1,
      "worldPosition": {
        "x": -117.407791,
        "y": 11.15374,
        "z": -225.115372
      },
      "quaternionRotation": {
        "x": -0.004015104,
        "y": -2.65911585E-05,
        "z": -0.00210265955,
        "w": 0.9999898
      },
      "floatData": null,
      "stringData": null
    },
    {
      "prefabName": "seed",
      "dimension": 1,
      "worldPosition": {
        "x": -119.107254,
        "y": 11.1471558,
        "z": -225.662354
      },
      "quaternionRotation": {
        "x": -0.00358131272,
        "y": 1.71348747E-05,
        "z": 0.00247458857,
        "w": 0.9999906
      },
      "floatData": null,
      "stringData": null
    },
    {
      "prefabName": "seed",
      "dimension": 1,
      "worldPosition": {
        "x": -234.645248,
        "y": 4.22936869,
        "z": -348.176361
      },
      "quaternionRotation": {
        "x": 0.00962534547,
        "y": -6.497685E-05,
        "z": 0.0105556585,
        "w": 0.999898
      },
      "floatData": null,
      "stringData": null
    },
    {
      "prefabName": "seed",
      "dimension": 1,
      "worldPosition": {
        "x": -271.831329,
        "y": 11.1500807,
        "z": 373.553925
      },
      "quaternionRotation": {
        "x": -0.004009573,
        "y": -5.949358E-05,
        "z": 0.00210865983,
        "w": 0.9999898
      },
      "floatData": null,
      "stringData": null
    },
    {
      "prefabName": "seed",
      "dimension": 1,
      "worldPosition": {
        "x": -161.384827,
        "y": 3.90481758,
        "z": 365.654358
      },
      "quaternionRotation": {
        "x": -0.0317860954,
        "y": 6.52795861E-05,
        "z": 0.0279996563,
        "w": 0.9991025
      },
      "floatData": null,
      "stringData": null
    },
    {
      "prefabName": "seed",
      "dimension": 1,
      "worldPosition": {
        "x": -255.856659,
        "y": 4.256269,
        "z": -341.83725
      },
      "quaternionRotation": {
        "x": 0.0122993244,
        "y": 1.81076084E-05,
        "z": 0.007309207,
        "w": 0.9998977
      },
      "floatData": null,
      "stringData": null
    },
    {
      "prefabName": "seed",
      "dimension": 1,
      "worldPosition": {
        "x": -117.200562,
        "y": 11.0974541,
        "z": -228.630371
      },
      "quaternionRotation": {
        "x": -0.0137330946,
        "y": -3.62015E-06,
        "z": -0.003366311,
        "w": 0.999900043
      },
      "floatData": null,
      "stringData": null
    },
    {
      "prefabName": "seed",
      "dimension": 1,
      "worldPosition": {
        "x": -121.361794,
        "y": 11.1345425,
        "z": -224.2211
      },
      "quaternionRotation": {
        "x": 0.001936485,
        "y": 3.805139E-05,
        "z": 0.007863925,
        "w": 0.9999673
      },
      "floatData": null,
      "stringData": null
    },
    {
      "prefabName": "seed",
      "dimension": 1,
      "worldPosition": {
        "x": 334.604523,
        "y": 4.201479,
        "z": -74.55154
      },
      "quaternionRotation": {
        "x": 0.001704483,
        "y": -0.000124815051,
        "z": 0.0140370531,
        "w": 0.999900043
      },
      "floatData": null,
      "stringData": null
    },
    {
      "prefabName": "seed",
      "dimension": 1,
      "worldPosition": {
        "x": -119.570335,
        "y": 11.119729,
        "z": -227.580627
      },
      "quaternionRotation": {
        "x": -0.012533783,
        "y": 2.90532334E-05,
        "z": 0.00657945964,
        "w": 0.9998998
      },
      "floatData": null,
      "stringData": null
    },
    {
      "prefabName": "seed",
      "dimension": 1,
      "worldPosition": {
        "x": -265.497284,
        "y": 4.1070137,
        "z": -334.762817
      },
      "quaternionRotation": {
        "x": 0.0203031581,
        "y": 0.0003771031,
        "z": -0.0160035547,
        "w": 0.9996657
      },
      "floatData": null,
      "stringData": null
    },
    {
      "prefabName": "seed",
      "dimension": 1,
      "worldPosition": {
        "x": -120.319839,
        "y": 11.0646381,
        "z": -229.385391
      },
      "quaternionRotation": {
        "x": -0.0125173861,
        "y": 5.127065E-05,
        "z": 0.006551194,
        "w": 0.999900162
      },
      "floatData": null,
      "stringData": null
    },
    {
      "prefabName": "seed",
      "dimension": 1,
      "worldPosition": {
        "x": -276.075226,
        "y": 4.05584335,
        "z": -330.584229
      },
      "quaternionRotation": {
        "x": 0.0258469265,
        "y": 0.000558009,
        "z": 0.00143415725,
        "w": 0.9996648
      },
      "floatData": null,
      "stringData": null
    },
    {
      "prefabName": "seed",
      "dimension": 1,
      "worldPosition": {
        "x": 269.118164,
        "y": 3.91165686,
        "z": 246.015442
      },
      "quaternionRotation": {
        "x": 0.0372620746,
        "y": -7.47375452E-05,
        "z": 0.0194924865,
        "w": 0.999115467
      },
      "floatData": null,
      "stringData": null
    },
    {
      "prefabName": "seed",
      "dimension": 1,
      "worldPosition": {
        "x": -244.647156,
        "y": 4.21415949,
        "z": -341.8143
      },
      "quaternionRotation": {
        "x": 0.0111138932,
        "y": 1.39995263E-05,
        "z": -0.0088254055,
        "w": 0.9998993
      },
      "floatData": null,
      "stringData": null
    },
    {
      "prefabName": "seed",
      "dimension": 1,
      "worldPosition": {
        "x": 344.729828,
        "y": 3.99655533,
        "z": -89.66305
      },
      "quaternionRotation": {
        "x": -0.0258781314,
        "y": 0.000175930589,
        "z": 3.5119956E-05,
        "w": 0.9996651
      },
      "floatData": null,
      "stringData": null
    },
    {
      "prefabName": "seed",
      "dimension": 1,
      "worldPosition": {
        "x": -268.127747,
        "y": 11.1281567,
        "z": 372.819641
      },
      "quaternionRotation": {
        "x": -0.008024945,
        "y": -0.0001435076,
        "z": -0.0116163725,
        "w": 0.999900341
      },
      "floatData": null,
      "stringData": null
    },
    {
      "prefabName": "seed",
      "dimension": 1,
      "worldPosition": {
        "x": 283.766785,
        "y": 3.99449229,
        "z": 242.876434
      },
      "quaternionRotation": {
        "x": 0.0194328241,
        "y": -0.0003394761,
        "z": -0.0172109623,
        "w": 0.999662936
      },
      "floatData": null,
      "stringData": null
    },
    {
      "prefabName": "seed",
      "dimension": 1,
      "worldPosition": {
        "x": -246.5224,
        "y": 4.24596167,
        "z": -341.766541
      },
      "quaternionRotation": {
        "x": 0.0112612555,
        "y": 3.26553345E-05,
        "z": -0.008856428,
        "w": 0.9998974
      },
      "floatData": null,
      "stringData": null
    },
    {
      "prefabName": "seed",
      "dimension": 1,
      "worldPosition": {
        "x": -268.628174,
        "y": 11.143074,
        "z": 375.6248
      },
      "quaternionRotation": {
        "x": 0.001591094,
        "y": 3.229393E-05,
        "z": -0.0042244806,
        "w": 0.999989867
      },
      "floatData": null,
      "stringData": null
    },
    {
      "prefabName": "seed",
      "dimension": 1,
      "worldPosition": {
        "x": 257.916016,
        "y": 3.71907663,
        "z": 224.39743
      },
      "quaternionRotation": {
        "x": -0.0151545964,
        "y": 4.587429E-05,
        "z": 0.039442867,
        "w": 0.999106944
      },
      "floatData": null,
      "stringData": null
    },
    {
      "prefabName": "seed",
      "dimension": 1,
      "worldPosition": {
        "x": -117.439888,
        "y": 11.1323175,
        "z": -220.578842
      },
      "quaternionRotation": {
        "x": 0.013836503,
        "y": -7.88010948E-05,
        "z": -0.00337664341,
        "w": 0.9998986
      },
      "floatData": null,
      "stringData": null
    },
    {
      "prefabName": "seed",
      "dimension": 1,
      "worldPosition": {
        "x": 266.839355,
        "y": 4.250766,
        "z": 227.843231
      },
      "quaternionRotation": {
        "x": -0.00504516438,
        "y": -0.000104974344,
        "z": 0.0133524956,
        "w": 0.999898136
      },
      "floatData": null,
      "stringData": null
    },
    {
      "prefabName": "seed",
      "dimension": 1,
      "worldPosition": {
        "x": -160.207275,
        "y": 4.051969,
        "z": 367.9815
      },
      "quaternionRotation": {
        "x": -0.01945101,
        "y": -0.00035096737,
        "z": 0.0171527714,
        "w": 0.9996636
      },
      "floatData": null,
      "stringData": null
    },
    {
      "prefabName": "seed",
      "dimension": 1,
      "worldPosition": {
        "x": 344.834534,
        "y": 4.225695,
        "z": -84.63519
      },
      "quaternionRotation": {
        "x": -0.0141511159,
        "y": 0.000105688945,
        "z": 5.2667383E-06,
        "w": 0.9998999
      },
      "floatData": null,
      "stringData": null
    },
    {
      "prefabName": "seed",
      "dimension": 1,
      "worldPosition": {
        "x": 257.764618,
        "y": 3.78278852,
        "z": 227.27388
      },
      "quaternionRotation": {
        "x": -0.00525662,
        "y": 1.96018445E-05,
        "z": 0.04185708,
        "w": 0.999109864
      },
      "floatData": null,
      "stringData": null
    },
    {
      "prefabName": "seed",
      "dimension": 1,
      "worldPosition": {
        "x": -119.83989,
        "y": 11.1477852,
        "z": -223.437057
      },
      "quaternionRotation": {
        "x": 0.00160930294,
        "y": 2.49151526E-07,
        "z": 0.00423548138,
        "w": 0.999989748
      },
      "floatData": null,
      "stringData": null
    },
    {
      "prefabName": "seed",
      "dimension": 1,
      "worldPosition": {
        "x": -118.461426,
        "y": 11.1283312,
        "z": -227.5889
      },
      "quaternionRotation": {
        "x": -0.0136745069,
        "y": 0.00013765342,
        "z": 0.00320787588,
        "w": 0.999901354
      },
      "floatData": null,
      "stringData": null
    },
    {
      "prefabName": "seed",
      "dimension": 1,
      "worldPosition": {
        "x": 335.264435,
        "y": 4.203906,
        "z": -71.63876
      },
      "quaternionRotation": {
        "x": 0.005011039,
        "y": -0.000129045176,
        "z": 0.0132117774,
        "w": 0.999900162
      },
      "floatData": null,
      "stringData": null
    },
    {
      "prefabName": "seed",
      "dimension": 1,
      "worldPosition": {
        "x": 261.997437,
        "y": 3.93968916,
        "z": 222.2064
      },
      "quaternionRotation": {
        "x": -0.0241821222,
        "y": 3.89276829E-05,
        "z": 0.03474086,
        "w": 0.9991038
      },
      "floatData": null,
      "stringData": null
    },
    {
      "prefabName": "seed",
      "dimension": 1,
      "worldPosition": {
        "x": -248.096771,
        "y": 4.35343075,
        "z": -351.409241
      },
      "quaternionRotation": {
        "x": -0.00238276226,
        "y": -2.21852588E-05,
        "z": -0.0038908103,
        "w": 0.9999897
      },
      "floatData": null,
      "stringData": null
    },
    {
      "prefabName": "seed",
      "dimension": 1,
      "worldPosition": {
        "x": -274.045,
        "y": 11.1360731,
        "z": 373.9697
      },
      "quaternionRotation": {
        "x": -0.001604774,
        "y": 1.29926657E-05,
        "z": 0.0042384495,
        "w": 0.9999898
      },
      "floatData": null,
      "stringData": null
    },
    {
      "prefabName": "seed",
      "dimension": 1,
      "worldPosition": {
        "x": -269.7777,
        "y": 11.1520233,
        "z": 374.214325
      },
      "quaternionRotation": {
        "x": -0.00257739914,
        "y": -1.05036524E-05,
        "z": -0.00372762582,
        "w": 0.9999898
      },
      "floatData": null,
      "stringData": null
    },
    {
      "prefabName": "seed",
      "dimension": 1,
      "worldPosition": {
        "x": -122.0611,
        "y": 11.09149,
        "z": -226.738556
      },
      "quaternionRotation": {
        "x": -0.008036424,
        "y": -5.670165E-05,
        "z": 0.0116495928,
        "w": 0.999899864
      },
      "floatData": null,
      "stringData": null
    },
    {
      "prefabName": "seed",
      "dimension": 1,
      "worldPosition": {
        "x": -233.7521,
        "y": 4.191948,
        "z": -345.8191
      },
      "quaternionRotation": {
        "x": 0.0119958594,
        "y": 1.06593707E-05,
        "z": 0.007979133,
        "w": 0.9998963
      },
      "floatData": null,
      "stringData": null
    },
    {
      "prefabName": "seed",
      "dimension": 1,
      "worldPosition": {
        "x": -270.662384,
        "y": 4.352801,
        "z": -346.4495
      },
      "quaternionRotation": {
        "x": -0.00238414225,
        "y": -2.85259375E-06,
        "z": -0.00390779926,
        "w": 0.999989569
      },
      "floatData": null,
      "stringData": null
    },
    {
      "prefabName": "seed",
      "dimension": 1,
      "worldPosition": {
        "x": -122.88575,
        "y": 11.08315,
        "z": -225.760742
      },
      "quaternionRotation": {
        "x": -0.00501672039,
        "y": -9.35421558E-05,
        "z": 0.0132315941,
        "w": 0.9998999
      },
      "floatData": null,
      "stringData": null
    },
    {
      "prefabName": "seed",
      "dimension": 1,
      "worldPosition": {
        "x": -160.820663,
        "y": 4.1442275,
        "z": 371.55127
      },
      "quaternionRotation": {
        "x": -0.0146616912,
        "y": -0.000533455,
        "z": 0.02126485,
        "w": 0.9996662
      },
      "floatData": null,
      "stringData": null
    },
    {
      "prefabName": "seed",
      "dimension": 1,
      "worldPosition": {
        "x": -157.777573,
        "y": 4.18682146,
        "z": 369.325836
      },
      "quaternionRotation": {
        "x": -0.0196452681,
        "y": -0.000128458676,
        "z": 0.017179098,
        "w": 0.9996594
      },
      "floatData": null,
      "stringData": null
    },
    {
      "prefabName": "seed",
      "dimension": 1,
      "worldPosition": {
        "x": -162.30098,
        "y": 4.003093,
        "z": 368.872925
      },
      "quaternionRotation": {
        "x": -0.0146592567,
        "y": -0.000533554936,
        "z": 0.0212623645,
        "w": 0.999666333
      },
      "floatData": null,
      "stringData": null
    },
    {
      "prefabName": "seed",
      "dimension": 1,
      "worldPosition": {
        "x": 268.9834,
        "y": 4.328475,
        "z": 230.743088
      },
      "quaternionRotation": {
        "x": -0.00178728939,
        "y": 0.0001523197,
        "z": 0.0142204762,
        "w": 0.999897242
      },
      "floatData": null,
      "stringData": null
    },
    {
      "prefabName": "seed",
      "dimension": 1,
      "worldPosition": {
        "x": 341.214417,
        "y": 4.283371,
        "z": -81.5315
      },
      "quaternionRotation": {
        "x": -0.0125361094,
        "y": 8.486707E-05,
        "z": 0.00657819537,
        "w": 0.999899745
      },
      "floatData": null,
      "stringData": null
    },
    {
      "prefabName": "seed",
      "dimension": 1,
      "worldPosition": {
        "x": -124.666443,
        "y": 10.9095678,
        "z": -230.352448
      },
      "quaternionRotation": {
        "x": -0.0193494428,
        "y": -0.000213886844,
        "z": 0.0171500687,
        "w": 0.9996657
      },
      "floatData": null,
      "stringData": null
    },
    {
      "prefabName": "seed",
      "dimension": 1,
      "worldPosition": {
        "x": -271.591278,
        "y": 11.1562891,
        "z": 375.787231
      },
      "quaternionRotation": {
        "x": 0.00339301187,
        "y": 1.44051846E-05,
        "z": 0.00300092972,
        "w": 0.999989748
      },
      "floatData": null,
      "stringData": null
    },
    {
      "prefabName": "seed",
      "dimension": 1,
      "worldPosition": {
        "x": -244.61438,
        "y": 4.2677393,
        "z": -344.779144
      },
      "quaternionRotation": {
        "x": 0.008818785,
        "y": -2.94445763E-05,
        "z": -0.0112770386,
        "w": 0.99989754
      },
      "floatData": null,
      "stringData": null
    },
    {
      "prefabName": "seed",
      "dimension": 1,
      "worldPosition": {
        "x": 337.507233,
        "y": 4.279653,
        "z": -76.43995
      },
      "quaternionRotation": {
        "x": -0.001706052,
        "y": -0.000115958326,
        "z": 0.014041435,
        "w": 0.9999
      },
      "floatData": null,
      "stringData": null
    },
    {
      "prefabName": "seed",
      "dimension": 1,
      "worldPosition": {
        "x": 260.7677,
        "y": 3.96565628,
        "z": 225.4849
      },
      "quaternionRotation": {
        "x": -0.009254403,
        "y": -0.0006855152,
        "z": 0.0241631437,
        "w": 0.999665
      },
      "floatData": null,
      "stringData": null
    },
    {
      "prefabName": "seed",
      "dimension": 1,
      "worldPosition": {
        "x": 274.1207,
        "y": 4.047105,
        "z": 244.681625
      },
      "quaternionRotation": {
        "x": 0.0259026866,
        "y": 0.000516950153,
        "z": -2.823901E-05,
        "w": 0.999664366
      },
      "floatData": null,
      "stringData": null
    },
    {
      "prefabName": "seed",
      "dimension": 1,
      "worldPosition": {
        "x": -158.707657,
        "y": 4.219353,
        "z": 371.8999
      },
      "quaternionRotation": {
        "x": -0.008143909,
        "y": -6.30809E-05,
        "z": 0.0117533151,
        "w": 0.999897838
      },
      "floatData": null,
      "stringData": null
    },
    {
      "prefabName": "seed",
      "dimension": 1,
      "worldPosition": {
        "x": 340.125275,
        "y": 4.34478474,
        "z": -74.55523
      },
      "quaternionRotation": {
        "x": 0.000548263954,
        "y": 5.745189E-05,
        "z": 0.004499596,
        "w": 0.999989748
      },
      "floatData": null,
      "stringData": null
    },
    {
      "prefabName": "seed",
      "dimension": 1,
      "worldPosition": {
        "x": -246.154892,
        "y": 4.179181,
        "z": -339.417175
      },
      "quaternionRotation": {
        "x": 0.0236269422,
        "y": 0.000569600437,
        "z": -0.0106928274,
        "w": 0.999663532
      },
      "floatData": null,
      "stringData": null
    },
    {
      "prefabName": "seed",
      "dimension": 1,
      "worldPosition": {
        "x": -154.560623,
        "y": 4.298743,
        "z": 371.8067
      },
      "quaternionRotation": {
        "x": -0.012684633,
        "y": 6.206871E-05,
        "z": 0.0066459123,
        "w": 0.99989754
      },
      "floatData": null,
      "stringData": null
    },
    {
      "prefabName": "seed",
      "dimension": 1,
      "worldPosition": {
        "x": -226.607819,
        "y": 4.224219,
        "z": -345.4124
      },
      "quaternionRotation": {
        "x": 0.0142451469,
        "y": 0.000107548338,
        "z": -0.00188256311,
        "w": 0.999896765
      },
      "floatData": null,
      "stringData": null
    },
    {
      "prefabName": "seed",
      "dimension": 1,
      "worldPosition": {
        "x": -154.271439,
        "y": 4.28005838,
        "z": 370.909668
      },
      "quaternionRotation": {
        "x": -0.012525117,
        "y": 2.55648738E-05,
        "z": 0.00657942472,
        "w": 0.9998999
      },
      "floatData": null,
      "stringData": null
    },
    {
      "prefabName": "seed",
      "dimension": 1,
      "worldPosition": {
        "x": -249.293472,
        "y": 4.36001,
        "z": -346.6996
      },
      "quaternionRotation": {
        "x": 0.003612853,
        "y": 1.805694E-05,
        "z": -0.00282597239,
        "w": 0.9999895
      },
      "floatData": null,
      "stringData": null
    },
    {
      "prefabName": "seed",
      "dimension": 1,
      "worldPosition": {
        "x": -225.107285,
        "y": 4.09670639,
        "z": -342.552551
      },
      "quaternionRotation": {
        "x": 0.0256747268,
        "y": 0.00057602,
        "z": -0.00339614321,
        "w": 0.9996644
      },
      "floatData": null,
      "stringData": null
    },
    {
      "prefabName": "seed",
      "dimension": 1,
      "worldPosition": {
        "x": -275.020569,
        "y": 11.1133537,
        "z": 376.031982
      },
      "quaternionRotation": {
        "x": 0.005020477,
        "y": 5.141655E-05,
        "z": 0.013259666,
        "w": 0.999899566
      },
      "floatData": null,
      "stringData": null
    },
    {
      "prefabName": "seed",
      "dimension": 1,
      "worldPosition": {
        "x": -261.59256,
        "y": 3.986273,
        "z": -335.744171
      },
      "quaternionRotation": {
        "x": 0.0159078669,
        "y": 0.000221814218,
        "z": -0.0203887057,
        "w": 0.999665558
      },
      "floatData": null,
      "stringData": null
    },
    {
      "prefabName": "seed",
      "dimension": 1,
      "worldPosition": {
        "x": -154.556351,
        "y": 4.349312,
        "z": 375.3026
      },
      "quaternionRotation": {
        "x": -0.00257560145,
        "y": 1.4339792E-05,
        "z": 0.00373031688,
        "w": 0.999989748
      },
      "floatData": null,
      "stringData": null
    },
    {
      "prefabName": "seed",
      "dimension": 1,
      "worldPosition": {
        "x": -268.026764,
        "y": 4.0754447,
        "z": -332.290619
      },
      "quaternionRotation": {
        "x": 0.0235673673,
        "y": 0.000619370432,
        "z": -0.0106883775,
        "w": 0.999664962
      },
      "floatData": null,
      "stringData": null
    },
    {
      "prefabName": "seed",
      "dimension": 1,
      "worldPosition": {
        "x": -123.52005,
        "y": 11.0315657,
        "z": -227.985977
      },
      "quaternionRotation": {
        "x": -0.0147684738,
        "y": -0.000306443544,
        "z": 0.0212624427,
        "w": 0.999664843
      },
      "floatData": null,
      "stringData": null
    },
    {
      "prefabName": "seed",
      "dimension": 1,
      "worldPosition": {
        "x": 264.176331,
        "y": 3.95677185,
        "z": 219.967255
      },
      "quaternionRotation": {
        "x": -0.0193332545,
        "y": -0.000340705446,
        "z": 0.0171471238,
        "w": 0.999666
      },
      "floatData": null,
      "stringData": null
    },
    {
      "prefabName": "seed",
      "dimension": 1,
      "worldPosition": {
        "x": -271.498962,
        "y": 11.1354284,
        "z": 371.74115
      },
      "quaternionRotation": {
        "x": -0.00440227846,
        "y": -5.09532074E-05,
        "z": 0.00108585437,
        "w": 0.999989748
      },
      "floatData": null,
      "stringData": null
    },
    {
      "prefabName": "seed",
      "dimension": 1,
      "worldPosition": {
        "x": 338.524384,
        "y": 4.19536066,
        "z": -83.46294
      },
      "quaternionRotation": {
        "x": -0.0105922166,
        "y": -5.53526952E-05,
        "z": 0.00938797,
        "w": 0.999899864
      },
      "floatData": null,
      "stringData": null
    },
    {
      "prefabName": "seed",
      "dimension": 1,
      "worldPosition": {
        "x": -242.085022,
        "y": 4.2012887,
        "z": -344.538666
      },
      "quaternionRotation": {
        "x": 0.005816126,
        "y": -0.000100730751,
        "z": -0.0130291926,
        "w": 0.9998982
      },
      "floatData": null,
      "stringData": null
    },
    {
      "prefabName": "seed",
      "dimension": 1,
      "worldPosition": {
        "x": -267.371216,
        "y": 4.23901463,
        "z": -350.3328
      },
      "quaternionRotation": {
        "x": -0.010183895,
        "y": -0.000134373753,
        "z": -0.0100077894,
        "w": 0.999898136
      },
      "floatData": null,
      "stringData": null
    },
    {
      "prefabName": "seed",
      "dimension": 1,
      "worldPosition": {
        "x": -223.049179,
        "y": 4.268918,
        "z": -348.570465
      },
      "quaternionRotation": {
        "x": 0.0117057972,
        "y": 2.85697643E-05,
        "z": -0.008237769,
        "w": 0.99989754
      },
      "floatData": null,
      "stringData": null
    },
    {
      "prefabName": "seed",
      "dimension": 1,
      "worldPosition": {
        "x": -267.9404,
        "y": 11.1055393,
        "z": 371.8302
      },
      "quaternionRotation": {
        "x": -0.0105797183,
        "y": -6.671833E-05,
        "z": -0.00935709,
        "w": 0.9999003
      },
      "floatData": null,
      "stringData": null
    },
    {
      "prefabName": "monsterEggvidra_Hungry",
      "dimension": 1,
      "worldPosition": {
        "x": 346.389221,
        "y": 4.52748871,
        "z": -72.21328
      },
      "quaternionRotation": {
        "x": 1.997661E-06,
        "y": 2.24113464E-05,
        "z": 1.00886791E-05,
        "w": 1.0
      },
      "floatData": {
        "timeToHatch": 150.0
      },
      "stringData": null
    },
    {
      "prefabName": "monsterEggSkufidron",
      "dimension": 1,
      "worldPosition": {
        "x": -120.999611,
        "y": 3.38020158,
        "z": -225.000168
      },
      "quaternionRotation": {
        "x": -0.000383784529,
        "y": -2.17854977E-05,
        "z": -0.00107001571,
        "w": 0.9999994
      },
      "floatData": {
        "timeToHatch": 150.0
      },
      "stringData": null
    },
    {
      "prefabName": "monsterEggAksolotl",
      "dimension": 1,
      "worldPosition": {
        "x": -151.5438,
        "y": 4.465215,
        "z": 370.797272
      },
      "quaternionRotation": {
        "x": -9.998959E-06,
        "y": 2.08616228E-07,
        "z": 1.01720152E-08,
        "w": 1.0
      },
      "floatData": {
        "timeToHatch": 150.0
      },
      "stringData": null
    },
    {
      "prefabName": "log",
      "dimension": 1,
      "worldPosition": {
        "x": -327.908264,
        "y": 4.2398715,
        "z": 59.31029
      },
      "quaternionRotation": {
        "x": 0.061490912,
        "y": -0.159109175,
        "z": 0.6572092,
        "w": 0.734152
      },
      "floatData": null,
      "stringData": null
    },
    {
      "prefabName": "log",
      "dimension": 1,
      "worldPosition": {
        "x": -327.6592,
        "y": 4.196698,
        "z": 60.50035
      },
      "quaternionRotation": {
        "x": 0.194139242,
        "y": -0.0197246615,
        "z": 0.6355932,
        "w": 0.7469554
      },
      "floatData": null,
      "stringData": null
    },
    {
      "prefabName": "log",
      "dimension": 1,
      "worldPosition": {
        "x": -328.002777,
        "y": 4.181579,
        "z": 61.6132965
      },
      "quaternionRotation": {
        "x": -0.5375511,
        "y": -0.6723846,
        "z": 0.411005974,
        "w": 0.30001992
      },
      "floatData": null,
      "stringData": null
    }
  ],
  "SavedFloats": {
    "shouldShowTask": 1.0,
    "dimension": 2.0,
    "currentTaskIndex": 0.0,
    "shouldShowTutorial": 0.0,
    "tutorialIndex": 5.0,
    "smola": 1.0,
    "logs": 0.0,
    "seeds": 0.0,
    "Lev": 0.0,
    "LevCompleted": 0.0,
    "LevIntroduced": 0.0,
    "Nadeshda": 0.0,
    "NadeshdaCompleted": 0.0,
    "NadeshdaIntroduced": 0.0,
    "Daria": 0.0,
    "DariaCompleted": 0.0,
    "DariaIntroduced": 0.0,
    "Matvey": 0.0,
    "MatveyCompleted": 0.0,
    "MatveyIntroduced": 0.0,
    "fiatX": -14.4098806,
    "fiatY": 4.32765,
    "fiatZ": 6.030671,
    "fiatQX": 0.033351168,
    "fiatQY": -0.5259835,
    "fiatQZ": 0.0255530961,
    "fiatQW": 0.84945637,
    "isMounted": 0.0,
    "DedMiron": 1.0,
    "DedMironCompleted": 0.0,
    "DedMironIntroduced": 1.0,
    "Aglaya": 0.0,
    "AglayaCompleted": 0.0,
    "AglayaIntroduced": 0.0,
    "Zahar": 0.0,
    "ZaharCompleted": 0.0,
    "ZaharIntroduced": 0.0,
    "Kassandra": 0.0,
    "KassandraCompleted": 0.0,
    "KassandraIntroduced": 0.0,
    "playerX": -13.0315685,
    "playerY": 5.03598976,
    "playerZ": 4.015973,
    "infuserSmola": 0.0
  },
  "SavedStrings": {
    "currentNpcTaskName": "DedMiron"
  }
}